slack_exception_logger/__init__.py
slack_exception_logger/slack_exception_logger.py
slack_exception_logger-0.3.dist-info/LICENSE
slack_exception_logger-0.3.dist-info/METADATA
slack_exception_logger-0.3.dist-info/WHEEL
slack_exception_logger-0.3.dist-info/top_level.txt
slack_exception_logger-0.3.dist-info/RECORD
