Metadata-Version: 2.1
Name: slack-exception-logger
Version: 0.3
Summary: A Python library for logging exceptions to a Slack channel
Home-page: https://github.com/dillibk777/slack_exception_logger
Author: Dilli Babu Kadati
Author-email: dillibabukadati777@gmail.com
Classifier: Programming Language :: Python :: 3
Classifier: License :: OSI Approved :: MIT License
Classifier: Operating System :: OS Independent
License-File: LICENSE
Requires-Dist: requests
